README.rst
setup.cfg
setup.py
rest_query/__init__.py
rest_query/models.py
rest_query/operator.py
rest_query/parser.py
rest_query/query.py
rest_query/serializer.py
rest_query.egg-info/PKG-INFO
rest_query.egg-info/SOURCES.txt
rest_query.egg-info/dependency_links.txt
rest_query.egg-info/top_level.txt